langumo_ko/__init__.py
langumo_ko/utils.py
langumo_ko/moducorpus/__init__.py
langumo_ko/moducorpus/base.py
langumo_ko/moducorpus/parsing.py
langumo_ko/namuwiki/__init__.py
langumo_ko/namuwiki/parsing.py
langumo_ko/namuwiki/rendering.py
langumo_ko-0.1.4.dist-info/LICENSE
langumo_ko-0.1.4.dist-info/METADATA
langumo_ko-0.1.4.dist-info/WHEEL
langumo_ko-0.1.4.dist-info/top_level.txt
langumo_ko-0.1.4.dist-info/RECORD
