Metadata-Version: 2.1
Name: langumo-ko
Version: 0.1.4
Summary: 한국어 말뭉치용 langumo parser 모음
Home-page: https://github.com/affjljoo3581/langumo-ko
Author: Jungwoo Park
Author-email: affjljoo3581@gmail.com
License: Apache-2.0
Keywords: langumo,corpus,dataset,nlp,language-model,deep-learning,machine-learning,korean
Platform: UNKNOWN
Classifier: Environment :: Console
Classifier: Operating System :: OS Independent
Classifier: Programming Language :: Python :: 3
Classifier: Programming Language :: Python :: 3.6
Classifier: Programming Language :: Python :: 3.7
Classifier: Programming Language :: Python :: 3.8
Classifier: Topic :: Scientific/Engineering :: Artificial Intelligence
Requires-Python: >=3.6.0
Requires-Dist: langumo
Requires-Dist: ijson (>=3.1.1)
